torchhull/__init__.py
torchhull/_C/CMakeLists.txt
torchhull/_C/include/torchhull/cuda_utils.h
torchhull/_C/include/torchhull/gaussian_blur.h
torchhull/_C/include/torchhull/image_utils.h
torchhull/_C/include/torchhull/io.h
torchhull/_C/include/torchhull/marching_cubes.h
torchhull/_C/include/torchhull/marching_cubes_utils.h
torchhull/_C/include/torchhull/math.h
torchhull/_C/include/torchhull/preprocessor.h
torchhull/_C/include/torchhull/ravelled_sparse_tensor.h
torchhull/_C/include/torchhull/stdgpu_allocator.h
torchhull/_C/include/torchhull/visual_hull.h
torchhull/_C/python/bindings.cpp
torchhull/_C/src/gaussian_blur.cpp
torchhull/_C/src/gaussian_blur_cuda.cu
torchhull/_C/src/io.cpp
torchhull/_C/src/marching_cubes.cpp
torchhull/_C/src/marching_cubes_cuda.cu
torchhull/_C/src/marching_cubes_table.h
torchhull/_C/src/visual_hull.cpp
torchhull/_C/src/visual_hull_cuda.cu
torchhull-0.3.0.dist-info/licenses/LICENSE
torchhull-0.3.0.dist-info/METADATA
torchhull-0.3.0.dist-info/WHEEL
torchhull-0.3.0.dist-info/top_level.txt
torchhull-0.3.0.dist-info/RECORD
