Metadata-Version: 2.4
Name: torchhull
Version: 0.3.0
Summary: A fast Visual Hull implementation
Author-email: Patrick Stotko <stotko@cs.uni-bonn.de>
Project-URL: Homepage, https://github.com/vc-bonn/torchhull
Project-URL: Repository, https://github.com/vc-bonn/torchhull
Project-URL: Documentation, https://vc-bonn.github.io/torchhull/
Project-URL: Changelog, https://github.com/vc-bonn/torchhull/blob/main/CHANGELOG.md
Classifier: Development Status :: 4 - Beta
Classifier: License :: OSI Approved :: MIT License
Classifier: License :: OSI Approved :: BSD License
Classifier: Programming Language :: C++
Classifier: Environment :: GPU :: NVIDIA CUDA
Classifier: Programming Language :: Python :: 3 :: Only
Classifier: Programming Language :: Python :: 3.10
Classifier: Programming Language :: Python :: 3.11
Classifier: Programming Language :: Python :: 3.12
Classifier: Programming Language :: Python :: 3.13
Classifier: Topic :: Scientific/Engineering :: Image Recognition
Classifier: Topic :: Scientific/Engineering :: Visualization
Classifier: Intended Audience :: Science/Research
Requires-Python: >=3.10
License-File: LICENSE
Requires-Dist: torch
Requires-Dist: charonload
Provides-Extra: dev
Requires-Dist: build; extra == "dev"
Requires-Dist: black~=25.0; extra == "dev"
Requires-Dist: isort; extra == "dev"
Requires-Dist: docformatter; extra == "dev"
Requires-Dist: clang-format~=14.0; extra == "dev"
Requires-Dist: ruff>=0.2; extra == "dev"
Requires-Dist: mypy; extra == "dev"
Requires-Dist: codespell; extra == "dev"
Requires-Dist: check-manifest; extra == "dev"
Requires-Dist: sphinx; extra == "dev"
Requires-Dist: furo; extra == "dev"
Requires-Dist: sphinx-autobuild; extra == "dev"
Requires-Dist: sphinx-autodoc-typehints>=2.0; extra == "dev"
Requires-Dist: sphinx_autodoc_defaultargs; extra == "dev"
Requires-Dist: sphinx_copybutton; extra == "dev"
Requires-Dist: myst-parser; extra == "dev"
Requires-Dist: docutils>=0.17; extra == "dev"
Requires-Dist: moderngl; extra == "dev"
Requires-Dist: numpy; extra == "dev"
Requires-Dist: pillow; extra == "dev"
Requires-Dist: pytest; extra == "dev"
Requires-Dist: pytest-benchmark; extra == "dev"
Requires-Dist: scipy; extra == "dev"
Requires-Dist: trimesh; extra == "dev"
Requires-Dist: nox; extra == "dev"
Dynamic: license-file
